naceconverter/NACEConverter.py
naceconverter/__init__.py
naceconverter/nacecodes.csv
naceconverter-1.0.1.dist-info/licenses/LICENSE
naceconverter-1.0.1.dist-info/METADATA
naceconverter-1.0.1.dist-info/WHEEL
naceconverter-1.0.1.dist-info/top_level.txt
naceconverter-1.0.1.dist-info/RECORD
