Metadata-Version: 2.4
Name: naceconverter
Version: 1.0.1
Summary: A Python package for converting NACE codes to descriptions and searching
Home-page: https://github.com/alexandersen01/nace-converter-py
Author: Jakob Alexandersen
Author-email: Jakob Alexandersen <jakob.alexandersen@fsncapital.com>
License: MIT
Project-URL: Homepage, https://github.com/alexandersen01/nace-converter-py
Project-URL: Repository, https://github.com/alexandersen01/nace-converter-py.git
Project-URL: Issues, https://github.com/alexandersen01/nace-converter-py/issues
Keywords: nace,codes,economic,activities,classification,converter,europe
Classifier: Development Status :: 5 - Production/Stable
Classifier: Intended Audience :: Developers
Classifier: Topic :: Software Development :: Libraries :: Python Modules
Classifier: License :: OSI Approved :: MIT License
Classifier: Programming Language :: Python :: 3
Classifier: Programming Language :: Python :: 3.8
Classifier: Programming Language :: Python :: 3.9
Classifier: Programming Language :: Python :: 3.10
Classifier: Programming Language :: Python :: 3.11
Classifier: Programming Language :: Python :: 3.12
Classifier: Programming Language :: Python :: 3.13
Classifier: Operating System :: OS Independent
Requires-Python: >=3.7
License-File: LICENSE
Dynamic: author
Dynamic: home-page
Dynamic: license-file
Dynamic: requires-python
